{
  "Menu": "Menu",
  "Search, Filter, Sort": "Search, Filter, Sort",
  "Settings": "Settings",
  "Categories": "Categories",
  "Data": "Data",
  "Priorities": "Priorities",
  "Trash": "Trash",
  "Help": "Help",

  "Habits": "Habits",
  "Notes": "Notes",
  "Tasks": "Tasks",

  "Add new note": "Add new note",
  "Add new habit": "Add new habit",
  "Add new task": "Add new task",

  "Search...": "...",
  "Search": "Search",
  "Filter": "Filter",
  "Filter by date": "Filter by date",
  "Filter by category": "Filter by category",
  "Filter by priority": "Filter by priority",
  "Filter by status": "Filter by status",
  "Sort": "Sort",
  "Home": "Home",
  "About": "About",
  "Add note text": "Add note text",
  "Color": "Color",
  "Category": "Category",
  "transparent": "transparent",
  "body": "body",
  "body secondary": "body secondary",
  "body tertiary": "body tertiary",
  "primary": "primary",
  "secondary": "secondary",
  "success": "success",
  "danger": "danger",
  "warning": "warning",
  "info": "info",
  "light": "light",
  "dark": "dark",
  "Planned at": "Planned at",
  "Duration": "Duration",
  "Repeat": "Repeat",
  "every": "every",
  "Start timer": "Start timer",
  "Total time spent": "Total time spent",
  "Average time spent": "Average time spent",
  "Repeat interval": "Repeat interval",
  "Elapsed time to repeat interval ratio": "Elapsed time to repeat interval ratio",
  "Repeat interval overdue": "Repeat interval overdue",
  "Average interval": "Average interval",
  "Elapsed time to average interval ratio": "Elapsed time to average interval ratio",
  "Average interval overdue": "Average interval overdue",
  "Average interval to repeat interval ratio": "Average interval to repeat interval ratio",
  "Started": "Started",
  "Completed": "Completed",
  "times, last time on": "times, last time on",
  "Created": "Created",
  "Updated": "Updated",
  "Add new item": "Add new item",
  "Mo": "Mo",
  "Tu": "Tu",
  "We": "We",
  "Th": "Th",
  "Fr": "Fr",
  "Sa": "Sa",
  "Su": "Su",
  "From": "From",
  "to": "to",
  "Restore all": "Restore all",
  "Restore": "Restore",
  "Empty trash": "Empty trash",
  "Add new category": "Add new category",
  "Dark mode": "Dark mode",
  "Theme": "Theme",
  "Start page": "Start page",
  "Start sidebar": "Start sidebar",
  "Show help": "Show help",
  "Show priority": "Show priority",
  "Show item list": "Show item list",
  "Show small calendar": "Show small calendar",
  "Show large calendar": "Show large calendar",
  "Show habit statistics": "Show habit statistics",
  "Show category": "Show category",
  "Show color": "Show color",
  "Show created & updated": "Show created & updated",
  "Language": "Language",
  "Week start": "Week start",
  "Display category filter as": "Display category filter as",
  "Display priority filter as": "Display priority filter as",
  "Check boxes": "Check boxes",
  "Radio buttons": "Radio buttons",
  "Drop down list": "Drop down list",
  "Horizontal space": "Horizontal space",
  "Vertical space": "Vertical space",
  "Insert tabs in note content": "Insert tabs in note content",
  "Display note content as Markdown": "Display note content as Markdown",
  "Reset habit when it is completed": "Reset habit when it is completed",
  "Load examples": "Load examples",
  "Delete all data": "Delete all data",
  "Import / Export": "Import / Export",
  "Export JSON": "Export JSON",
  "Export TSV": "Export TSV",
  "Export YAML": "Export YAML",
  "Export Markdown": "Export Markdown",
  "Import": "Import",
  "Online sync": "Online sync",
  "To enable online sync, run": "To enable online sync, run",
  "image on your server": "image on your server",
  "Address": "Address",
  "Username": "Username",
  "Password": "Password",
  "Remember me": "Remember me",
  "Log in": "Log in",
  "Log out": "Log out",
  "User": "User",
  "Invalid address": "Invalid address",
  "Invalid credentials": "Invalid credentials",
  "Connection error": "Connection error",
  "Planned": "Planned",
  "Done": "Done",
  "All": "All",
  "None": "None",
  "Very low": "Very low",
  "Low": "Low",
  "Medium": "Medium",
  "High": "High",
  "Very high": "Very high",
  "Hide completed tasks": "Hide completed tasks",
  "Habit interval ratio": "Habit interval ratio",
  "Show only habits with interval ratio over": "Show only habits with interval ratio over",

  "Day": "Day",
  "Week": "Week",
  "Month": "Month",
  "Year": "Year",
  "Sunday": "Sunday",
  "Monday": "Monday",
  "Tuesday": "Tuesday",
  "Wednesday": "Wednesday",
  "Thursday": "Thursday",
  "Friday": "Friday",
  "Saturday": "Saturday",
  "Elapsed time to average interval": "Elapsed time to average interval",
  "Elapsed time to repeat interval": "Elapsed time to repeat interval",
  "Average interval to repeat interval": "Average interval to repeat interval",
  "Priority": "Priority",
  "Title": "Title",
  "Elapsed time": "Elapsed time",
  "Time spent": "Time spent",
  "Selected interval ratio": "Selected interval ratio",

  "Previous week": "Previous week",
  "Previous month": "Previous month",
  "Next month": "Next month",
  "Next week": "Next week",
  "Decrease": "Decrease",
  "Increase": "Increase",
  "Save": "Save",
  "Delete": "Delete",
  "Start": "Start",
  "Reset": "Reset",
  "Pause": "Pause",
  "Stop": "Stop",
  "Add": "Add",
  "Close": "Close",
  "Match case": "Match case",

  "Version": "Version",
  "Take Markdown notes, plan tasks, track habits": "Take Markdown notes, plan tasks, track habits",
  "Free and Ad-Free": "Free and Ad-Free",
  "Open Source": "Open Source",
  "Privacy Focused: All user data is stored locally on your device": "Privacy Focused: All user data is stored locally on your device",
  "Available on Windows, Linux, Android, iOS, macOS, and as a web app": "Available on Windows, Linux, Android, iOS, macOS, and as a web app",
  "Localized to English, German, Spanish, Slovenian": "Localized to English, German, Spanish, Slovenian",
  "Key Features": "Key Features",
  "Markdown support for notes": "Markdown support for notes",
  "Use categories and priorities to organize your notes, tasks, and habits": "Use categories and priorities to organize your notes, tasks, and habits",
  "Advanced Search, Filter, and Sort": "Advanced Search, Filter, and Sort",
  "Data Export/Import: JSON, YAML, TSV, Markdown": "Data Export/Import: JSON, YAML, TSV, Markdown",
  "Import your notes from Google Keep": "Import your notes from Google Keep",
  "Available in 26 themes with Dark and Light modes": "Available in 26 themes with Dark and Light modes",

  "Privacy": "Privacy",
  "saves your data (notes, tasks and habits) on your device, offering you complete privacy.": "saves your data (notes, tasks and habits) on your device, offering you complete privacy.",
  "It allows you to delete the data stored on your device at any time.": "It allows you to delete the data stored on your device at any time.",
  "If you use the Docker image to enable online sync, all data is stored in your Docker container and is completely under your control.": "If you use the Docker image to enable online sync, all data is stored in your Docker container and is completely under your control.",
  "It is available on 6 platforms and on some platforms it can backup your data to your Google Drive.": "It is available on 6 platforms and on some platforms it can backup your data to your Google Drive.",
  "If you allow it to backup your data to your Google Drive, it will receive your email and display your name only on your device.": "If you allow it to backup your data to your Google Drive, it will receive your email and display your name only on your device.",
  "You can read the privacy policy at": "You can read the privacy policy at"
}
